trackotron/__init__.py
trackotron/_version.py
trackotron/contexts/__init__.py
trackotron/contexts/context.py
trackotron/contexts/event.py
trackotron/contexts/generation.py
trackotron/contexts/span.py
trackotron/observer.py
trackotron/proxies.py
trackotron/py.typed
trackotron/types_/__init__.py
trackotron/types_/compatibility.py
trackotron/types_/generics.py
trackotron/types_/misc.py
trackotron/updates.py
trackotron-0.1.0.dist-info/LICENSE
trackotron-0.1.0.dist-info/METADATA
trackotron-0.1.0.dist-info/WHEEL
trackotron-0.1.0.dist-info/RECORD
