Metadata-Version: 2.1
Name: trackotron
Version: 0.1.0
Summary: Improved decorator for Langfuse.
Home-page: https://github.com/bendabir/trackotron
License: GPL-3.0-or-later
Keywords: langfuse
Author: Bendabir
Requires-Python: >=3.9,<4
Classifier: License :: OSI Approved :: GNU General Public License v3 or later (GPLv3+)
Classifier: Programming Language :: Python :: 3
Classifier: Programming Language :: Python :: 3.9
Classifier: Programming Language :: Python :: 3.10
Classifier: Programming Language :: Python :: 3.11
Classifier: Programming Language :: Python :: 3.12
Requires-Dist: langfuse (>=2,<3)
Requires-Dist: typing-extensions (>=4.12.0,<5.0.0)
Project-URL: Documentation, https://github.com/Bendabir/trackotron/README.md
Project-URL: Repository, https://github.com/bendabir/trackotron
